inline_actions/__init__.py
inline_actions/actions.py
inline_actions/admin.py
inline_actions/static/inline_actions/css/inline_actions.css
inline_actions/templates/admin/extend_change_list.html
inline_actions/templatetags/__init__.py
inline_actions/templatetags/inline_action_tags.py
django4_inline_actions-2.1.dist-info/LICENSE
django4_inline_actions-2.1.dist-info/METADATA
django4_inline_actions-2.1.dist-info/WHEEL
django4_inline_actions-2.1.dist-info/RECORD
