Metadata-Version: 2.3
Name: django4-inline-actions
Version: 2.1
Summary: django4-inline-actions adds actions to each row of the ModelAdmin or InlineModelAdmin.
License: BSD-3-Clause
Author: Alexander Frenzel
Author-email: alex@relatedworks.com
Requires-Python: >=3.8,<4.0
Classifier: Development Status :: 4 - Beta
Classifier: Environment :: Web Environment
Classifier: Intended Audience :: Developers
Classifier: License :: OSI Approved :: BSD License
Classifier: Operating System :: OS Independent
Classifier: Programming Language :: Python
Classifier: Programming Language :: Python :: 3
Classifier: Programming Language :: Python :: 3.8
Classifier: Programming Language :: Python :: 3.9
Classifier: Programming Language :: Python :: 3.10
Classifier: Programming Language :: Python :: 3.11
Classifier: Programming Language :: Python :: 3.12
Classifier: Programming Language :: Python :: 3.13
Classifier: Topic :: Software Development :: Libraries :: Python Modules
Requires-Dist: django (>=3.0,<5.3)
Project-URL: Documentation, https://github.com/HiroshiFuu/django4-inline-actions/blob/master/README.md
Project-URL: Homepage, https://github.com/HiroshiFuu/django4-inline-actions
Project-URL: Repository, https://github.com/HiroshiFuu/django4-inline-actions
